netbox_webhook_receiver/__init__.py
netbox_webhook_receiver/api/__init__.py
netbox_webhook_receiver/api/serializers.py
netbox_webhook_receiver/api/urls.py
netbox_webhook_receiver/api/views.py
netbox_webhook_receiver/choices.py
netbox_webhook_receiver/filtersets.py
netbox_webhook_receiver/forms.py
netbox_webhook_receiver/migrations/0001_initial.py
netbox_webhook_receiver/migrations/0002_webhookreceiver_hash_algorithm.py
netbox_webhook_receiver/migrations/__init__.py
netbox_webhook_receiver/models.py
netbox_webhook_receiver/navigation.py
netbox_webhook_receiver/tables.py
netbox_webhook_receiver/templates/netbox_webhook_receiver/webhookreceiver.html
netbox_webhook_receiver/templates/netbox_webhook_receiver/webhookreceivergroup.html
netbox_webhook_receiver/urls.py
netbox_webhook_receiver/views/__init__.py
netbox_webhook_receiver/views/views.py
netbox_webhook_receiver/views/webhookreceiver.py
netbox_webhook_receiver/views/webhookreceivergroup.py
netbox_plugin_webhook_receiver-0.5.0.dist-info/LICENSE
netbox_plugin_webhook_receiver-0.5.0.dist-info/METADATA
netbox_plugin_webhook_receiver-0.5.0.dist-info/WHEEL
netbox_plugin_webhook_receiver-0.5.0.dist-info/RECORD
