Metadata-Version: 2.1
Name: netbox-plugin-webhook-receiver
Version: 0.5.0
Summary: NetBox Webhook is a plugin for managing webhook receivers in NetBox.
Home-page: https://github.com/LuPo/netbox-plugin-webhook-receiver
License: MIT
Keywords: netbox,netbox-plugin,webhook
Author: Łukasz Polański
Author-email: wookasz@gmail.com
Requires-Python: >=3.10,<4.0
Classifier: License :: OSI Approved :: MIT License
Classifier: Programming Language :: Python :: 3
Classifier: Programming Language :: Python :: 3.10
Classifier: Programming Language :: Python :: 3.11
Classifier: Programming Language :: Python :: 3.12
Project-URL: Repository, https://github.com/LuPo/netbox-plugin-webhook-receiver
